llama_index/readers/alibabacloud_aisearch/__init__.py
llama_index/readers/alibabacloud_aisearch/base.py
llama_index_readers_alibabacloud_aisearch-0.3.0.dist-info/METADATA
llama_index_readers_alibabacloud_aisearch-0.3.0.dist-info/WHEEL
llama_index_readers_alibabacloud_aisearch-0.3.0.dist-info/licenses/LICENSE
llama_index_readers_alibabacloud_aisearch-0.3.0.dist-info/RECORD
