Metadata-Version: 2.4
Name: llama-index-readers-alibabacloud-aisearch
Version: 0.3.0
Summary: llama-index readers alibabacloud_aisearch integration
Author: llama-index
License-Expression: MIT
License-File: LICENSE
Requires-Python: <4.0,>=3.9
Requires-Dist: alibabacloud-searchplat20240529<2,>=1.1.0
Requires-Dist: llama-index-core<0.14,>=0.13.0
